chronos.py
debugger.py
finder.py
jsons.py
keylogger.py
locus.py
multi.py
pixer.py
scrapy.py
typer.py
Utilities_py3-0.0.1.dist-info/LICENSE
Utilities_py3-0.0.1.dist-info/METADATA
Utilities_py3-0.0.1.dist-info/WHEEL
Utilities_py3-0.0.1.dist-info/top_level.txt
Utilities_py3-0.0.1.dist-info/RECORD
